{
  "Лекция 1": [
    {
      "Время/Неделя": "11:40-13:10"
    },
    {
      "Адрес/Аудитория": "ул.Ломоносова, д.9, лит. Е"
    },
    {
      "Предмет": "Иностранный язык(Прак)"
    },
    {
      "Формат": "Очно - дистанционный"
    }
  ],
  "Лекция 2": [
    {
      "Время/Неделя": "15:20-16:50"
    },
    {
      "Адрес/Аудитория": "304 ауд., Кронверкский пр., д.49, лит.А"
    },
    {
      "Предмет/Преподаватель": "Дискретная математика(Прак), Пинкевич Василий Юрьевич"
    },
    {
      "Формат": "Очно - дистанционный"
    }
  ]
}